odoo/addons/ssi_risk_analysis/README.rst
odoo/addons/ssi_risk_analysis/__init__.py
odoo/addons/ssi_risk_analysis/__manifest__.py
odoo/addons/ssi_risk_analysis/menu.xml
odoo/addons/ssi_risk_analysis/data/approval_template_data.xml
odoo/addons/ssi_risk_analysis/data/ir_sequence_data.xml
odoo/addons/ssi_risk_analysis/data/policy_template_data.xml
odoo/addons/ssi_risk_analysis/data/sequence_template_data.xml
odoo/addons/ssi_risk_analysis/demo/custom_info_option_demo.xml
odoo/addons/ssi_risk_analysis/demo/custom_info_option_set_demo.xml
odoo/addons/ssi_risk_analysis/demo/custom_info_property_demo.xml
odoo/addons/ssi_risk_analysis/demo/custom_info_template_demo.xml
odoo/addons/ssi_risk_analysis/demo/risk_analysis_result_demo.xml
odoo/addons/ssi_risk_analysis/demo/risk_analysis_type_demo.xml
odoo/addons/ssi_risk_analysis/demo/risk_analysis_worksheet_type_demo.xml
odoo/addons/ssi_risk_analysis/demo/risk_item_demo.xml
odoo/addons/ssi_risk_analysis/models/__init__.py
odoo/addons/ssi_risk_analysis/models/mixin_risk_analysis.py
odoo/addons/ssi_risk_analysis/models/risk_analysis.py
odoo/addons/ssi_risk_analysis/models/risk_analysis_conclusion.py
odoo/addons/ssi_risk_analysis/models/risk_analysis_item.py
odoo/addons/ssi_risk_analysis/models/risk_analysis_result.py
odoo/addons/ssi_risk_analysis/models/risk_analysis_standard_worksheet.py
odoo/addons/ssi_risk_analysis/models/risk_analysis_type.py
odoo/addons/ssi_risk_analysis/models/risk_analysis_type_conclusion.py
odoo/addons/ssi_risk_analysis/models/risk_analysis_type_item.py
odoo/addons/ssi_risk_analysis/models/risk_analysis_type_result.py
odoo/addons/ssi_risk_analysis/models/risk_analysis_worksheet.py
odoo/addons/ssi_risk_analysis/models/risk_analysis_worksheet_type.py
odoo/addons/ssi_risk_analysis/models/risk_item.py
odoo/addons/ssi_risk_analysis/models/risk_item_conclusion.py
odoo/addons/ssi_risk_analysis/models/risk_item_result.py
odoo/addons/ssi_risk_analysis/security/ir.model.access.csv
odoo14_addon_ssi_risk_analysis-14.0.2.5.0.dist-info/METADATA
odoo14_addon_ssi_risk_analysis-14.0.2.5.0.dist-info/WHEEL
odoo14_addon_ssi_risk_analysis-14.0.2.5.0.dist-info/top_level.txt
odoo14_addon_ssi_risk_analysis-14.0.2.5.0.dist-info/RECORD
